agent/__init__.py
agent/main.py
humblenode_agent-0.1.0.dist-info/METADATA
humblenode_agent-0.1.0.dist-info/WHEEL
humblenode_agent-0.1.0.dist-info/entry_points.txt
humblenode_agent-0.1.0.dist-info/RECORD
