Metadata-Version: 2.4
Name: humblenode-agent
Version: 0.1.0
Summary: HumbleNode agent (FastAPI + Typer)
Requires-Python: >=3.12
Requires-Dist: fastapi>=0.128.0
Requires-Dist: typer>=0.21.0
Requires-Dist: uvicorn>=0.40.0
